LICENSE
README.md
setup.cfg
setup.py
synonyms/__init__.py
synonyms/synonyms.py
synonyms/utils.py
synonyms/word2vec.py
synonyms.egg-info/PKG-INFO
synonyms.egg-info/SOURCES.txt
synonyms.egg-info/dependency_links.txt
synonyms.egg-info/requires.txt
synonyms.egg-info/top_level.txt
synonyms/data/dict.txt.big
synonyms/data/stopwords.txt
synonyms/data/vocab.txt