Metadata-Version: 2.4
Name: synonyms
Version: 3.25.0
Summary: 中文近义词：聊天机器人，智能问答工具包；Chinese Synonyms for Natural Language Processing and Understanding
Home-page: https://github.com/chatopera/Synonyms
Author: Hai Liang Wang, Hu Ying Xi
Author-email: hain@chatopera.com
License: Chunsong Public License, version 1.0
Keywords: corpus,machine-learning,NLU,NLP,Synonyms,Similarity,chatbot
Classifier: Intended Audience :: Developers
Classifier: Operating System :: OS Independent
Classifier: Natural Language :: Chinese (Simplified)
Classifier: Natural Language :: Chinese (Traditional)
Classifier: Programming Language :: Python
Classifier: Programming Language :: Python :: 3
Classifier: Programming Language :: Python :: 3.5
Classifier: Programming Language :: Python :: 3.6
Classifier: Programming Language :: Python :: 3.7
Classifier: Topic :: Text Processing
Classifier: Topic :: Text Processing :: Indexing
Classifier: Topic :: Text Processing :: Linguistic
License-File: LICENSE
Requires-Dist: six>=1.11.0
Requires-Dist: numpy>=1.20.0
Requires-Dist: scipy>=1.0.0
Requires-Dist: scikit-learn>=0.19.1
Requires-Dist: jieba>=0.42
Requires-Dist: chatoperastore>=1.2.0
Dynamic: author
Dynamic: author-email
Dynamic: classifier
Dynamic: description
Dynamic: home-page
Dynamic: keywords
Dynamic: license
Dynamic: license-file
Dynamic: requires-dist
Dynamic: summary
